[{"id":"1","name":"Homer Simpson"},{"id":"2","name":"Marge Simpson"},{"id":"3","name":"Bart Simpson"},{"id":"4","name":"Lisa Simpson"},{"id":"5","name":"Maggie Simpson"},{"id":"6","name":"Ned Flanders"},{"id":"7","name":"Montgomery Burns"},{"id":"8","name":"Nelson Muntz"},{"id":"9","name":"Krusty"},{"id":"10","name":"Milhouse Van Houten"},{},{"id":"56","name":"Fernanda"},{"id":"33","name":"Fernanda"},{"id":"59","name":"Fernanda"},{"id":"11232184","name":"Paulo"},{"id":"11284","name":"Paulo"},{"id":"55455569","name":"Fernanda"},{"id":"1888888","name":"Paulofffdf"}]